latexfixer/__init__.py
latexfixer/fix.py
latexfixer-0.1.4.dist-info/DESCRIPTION.rst
latexfixer-0.1.4.dist-info/METADATA
latexfixer-0.1.4.dist-info/RECORD
latexfixer-0.1.4.dist-info/WHEEL
latexfixer-0.1.4.dist-info/metadata.json
latexfixer-0.1.4.dist-info/top_level.txt
