Metadata-Version: 2.0
Name: latexfixer
Version: 0.1.4
Summary: Transform unicode text into typographically more correct LaTeX compatible unicode.
Home-page: https://github.com/thomasowenmclean/latexfixer
Author: Tom McLean
Author-email: thomasowenmclean@gmail.com
License: GPL
Keywords: latex
Platform: UNKNOWN
Classifier: Development Status :: 4 - Beta
Classifier: Topic :: Text Processing :: Markup :: LaTeX
Classifier: License :: OSI Approved :: GNU General Public License v2 (GPLv2)
Classifier: Programming Language :: Python :: 3
